apollo_orm/__init__.py
apollo_orm/domains/__init__.py
apollo_orm/domains/models/__init__.py
apollo_orm/domains/models/entities/__init__.py
apollo_orm/domains/models/entities/column/__init__.py
apollo_orm/domains/models/entities/column/entity.py
apollo_orm/domains/models/entities/concurrent/__init__.py
apollo_orm/domains/models/entities/concurrent/pre_processed_insert/__init__.py
apollo_orm/domains/models/entities/concurrent/pre_processed_insert/entity.py
apollo_orm/domains/models/entities/concurrent/result_list/__init__.py
apollo_orm/domains/models/entities/concurrent/result_list/entity.py
apollo_orm/domains/models/entities/concurrent/result_process/__init__.py
apollo_orm/domains/models/entities/concurrent/result_process/entity.py
apollo_orm/domains/models/entities/connection_config/__init__.py
apollo_orm/domains/models/entities/connection_config/entity.py
apollo_orm/domains/models/entities/credentials/__init__.py
apollo_orm/domains/models/entities/credentials/entity.py
apollo_orm/domains/models/entities/table_config/__init__.py
apollo_orm/domains/models/entities/table_config/entity.py
apollo_orm/orm/__init__.py
apollo_orm/orm/core.py
apollo_orm/orm/abstracts/__init__.py
apollo_orm/orm/abstracts/icredential.py
apollo_orm/orm/abstracts/idatabase.py
apollo_orm/orm/credentials/__init__.py
apollo_orm/orm/credentials/credential_service.py
apollo_orm/orm/credentials/json_credential_service.py
apollo_orm/orm/credentials/secrets_manager_credential_service.py
apollo_orm/utils/__init__.py
apollo_orm/utils/exceptions/CommonBaseException.py
apollo_orm/utils/exceptions/__init__.py
apollo_orm/utils/logger/__init__.py
apollo_orm/utils/logger/logger.py
apollo_orm-2.2.3.dist-info/LICENSE
apollo_orm-2.2.3.dist-info/METADATA
apollo_orm-2.2.3.dist-info/WHEEL
apollo_orm-2.2.3.dist-info/top_level.txt
apollo_orm-2.2.3.dist-info/RECORD
