Metadata-Version: 2.1
Name: apollo-orm
Version: 2.2.3
Summary: ORM Cassandra/Scylla Stable Version (2.x.x)
Author-email: Danilo Rodrigues <daniloarodrigues@outlook.com>
Project-URL: Homepage, https://github.com/daniloarodrigues/apollo-orm
Project-URL: Issues, https://github.com/daniloarodrigues/apollo-orm/issues
Classifier: Programming Language :: Python :: 3
Classifier: License :: OSI Approved :: MIT License
Classifier: Operating System :: OS Independent
Classifier: Development Status :: 4 - Beta
Classifier: Topic :: Database :: Database Engines/Servers
Requires-Python: >=3.9
License-File: LICENSE
